{
  "source": "/Users/tapir/Development/CadenzaOS/hardware/cadenza/working-base/Cadenza-reference-ESP32-S3-game-console-original-v2-20260722.kicad_sch",
  "output": "/Users/tapir/Development/CadenzaOS/hardware/cadenza/working-base/Cadenza-reference-ESP32-S3-game-console-original-v2-20260722.kicad_sch",
  "removed_sheet_pseudo_symbols": 1,
  "repaired_alias_bridges": [
    {
      "uuid": "0b1e07bd-3f78-4f87-b6d4-86c0d2535742",
      "functional_name": "TFT_DC",
      "canonical_pcb_net": "GPIO47",
      "renamed_labels": []
    },
    {
      "uuid": "16d3dc54-000e-4422-b264-df5911e26b41",
      "functional_name": "KEY_SELECT",
      "canonical_pcb_net": "GPIO16",
      "renamed_labels": []
    },
    {
      "uuid": "345f6e66-6587-430d-951c-c1ed261228d9",
      "functional_name": "KEY_UP",
      "canonical_pcb_net": "GPIO7",
      "renamed_labels": []
    },
    {
      "uuid": "364aefb8-67bb-497f-a065-1568cfdfe861",
      "functional_name": "TFT_MOSI",
      "canonical_pcb_net": "GPIO12",
      "renamed_labels": []
    },
    {
      "uuid": "4f0370ec-8e62-4f41-bc1f-57827b445146",
      "functional_name": "KEY_A",
      "canonical_pcb_net": "GPIO15",
      "renamed_labels": []
    },
    {
      "uuid": "583bbf3f-ca2c-4b4f-874e-57af0fd9fe56",
      "functional_name": "TFT_CS",
      "canonical_pcb_net": "GPIO14",
      "renamed_labels": []
    },
    {
      "uuid": "5fa403be-3500-475e-a41c-8cf9f3043518",
      "functional_name": "KEY_B",
      "canonical_pcb_net": "GPIO5",
      "renamed_labels": []
    },
    {
      "uuid": "63eaef46-3d4a-431d-aee1-b16df656f354",
      "functional_name": "SD_CMD",
      "canonical_pcb_net": "GPIO11",
      "renamed_labels": []
    },
    {
      "uuid": "69398faa-3906-4fbc-9d97-08c74e51e19b",
      "functional_name": "KEY_OPTION",
      "canonical_pcb_net": "GPIO8",
      "renamed_labels": []
    },
    {
      "uuid": "6f85750b-1f12-4cf3-88d9-372be63da4e3",
      "functional_name": "TFT_RST",
      "canonical_pcb_net": "GPIO3",
      "renamed_labels": []
    },
    {
      "uuid": "702d1844-c6ab-45fc-bb32-f70c469ae564",
      "functional_name": "SD_CLK",
      "canonical_pcb_net": "GPIO13",
      "renamed_labels": []
    },
    {
      "uuid": "8be6e0c9-9e8c-470d-b547-0d9bc9e7d2f6",
      "functional_name": "SD_CD",
      "canonical_pcb_net": "GPIO10",
      "renamed_labels": []
    },
    {
      "uuid": "8eda1147-17c4-4aef-b234-e7a4992c2010",
      "functional_name": "TFT_CLK",
      "canonical_pcb_net": "GPIO48",
      "renamed_labels": []
    },
    {
      "uuid": "97adecb9-a088-4dec-8f07-5e625bd8afcb",
      "functional_name": "TFT_BLK",
      "canonical_pcb_net": "GPIO39",
      "renamed_labels": []
    },
    {
      "uuid": "b39f0642-c7eb-4faf-bde0-b5b0e6302835",
      "functional_name": "KEY_RIGHT",
      "canonical_pcb_net": "GPIO6",
      "renamed_labels": []
    },
    {
      "uuid": "bbcbad2e-d93c-4609-acfd-6b23599ff0c5",
      "functional_name": "KEY_LEFT",
      "canonical_pcb_net": "GPIO19",
      "renamed_labels": []
    },
    {
      "uuid": "c3a1653c-58c0-4109-9bec-03f552ec45ee",
      "functional_name": "SD_DATA",
      "canonical_pcb_net": "GPIO9",
      "renamed_labels": []
    },
    {
      "uuid": "c5c42357-fea0-429e-bedd-3095e0ced0e3",
      "functional_name": "KEY_START",
      "canonical_pcb_net": "GPIO17",
      "renamed_labels": []
    },
    {
      "uuid": "e410a3cf-b250-48b0-9f40-95b9e48a7217",
      "functional_name": "KEY_MENU",
      "canonical_pcb_net": "GPIO18",
      "renamed_labels": []
    },
    {
      "uuid": "e625be41-6b2a-4d5c-9a30-0879a58864cd",
      "functional_name": "KEY_DOWN",
      "canonical_pcb_net": "GPIO20",
      "renamed_labels": []
    }
  ],
  "globally_renamed_labels": [
    {
      "from": "SD_DATA",
      "to": "GPIO9",
      "at": [
        33.782,
        254.508
      ]
    },
    {
      "from": "TFT_BLK",
      "to": "GPIO39",
      "at": [
        223.52,
        191.516
      ]
    },
    {
      "from": "KEY_OPTION",
      "to": "GPIO8",
      "at": [
        127.762,
        126.238
      ]
    },
    {
      "from": "TFT_CLK",
      "to": "GPIO48",
      "at": [
        223.52,
        196.596
      ]
    },
    {
      "from": "KEY_SELECT",
      "to": "GPIO16",
      "at": [
        127.762,
        136.398
      ]
    },
    {
      "from": "KEY_LEFT",
      "to": "GPIO19",
      "at": [
        196.596,
        153.924
      ]
    },
    {
      "from": "KEY_MENU",
      "to": "GPIO18",
      "at": [
        127.762,
        116.078
      ]
    },
    {
      "from": "TFT_CS",
      "to": "GPIO14",
      "at": [
        223.52,
        204.216
      ]
    },
    {
      "from": "TFT_MOSI",
      "to": "GPIO12",
      "at": [
        82.55,
        206.248
      ]
    },
    {
      "from": "TFT_DC",
      "to": "GPIO47",
      "at": [
        223.52,
        199.136
      ]
    },
    {
      "from": "SD_CLK",
      "to": "GPIO13",
      "at": [
        33.782,
        249.428
      ]
    },
    {
      "from": "KEY_START",
      "to": "GPIO17",
      "at": [
        127.762,
        146.558
      ]
    },
    {
      "from": "SD_CLK",
      "to": "GPIO13",
      "at": [
        98.044,
        248.412
      ]
    },
    {
      "from": "SD_CMD",
      "to": "GPIO11",
      "at": [
        33.782,
        244.348
      ]
    },
    {
      "from": "SD_CMD",
      "to": "GPIO11",
      "at": [
        98.044,
        243.332
      ]
    },
    {
      "from": "TFT_DC",
      "to": "GPIO47",
      "at": [
        82.55,
        198.628
      ]
    },
    {
      "from": "TFT_RST",
      "to": "GPIO3",
      "at": [
        223.52,
        201.676
      ]
    },
    {
      "from": "KEY_DOWN",
      "to": "GPIO20",
      "at": [
        196.596,
        159.004
      ]
    },
    {
      "from": "KEY_RIGHT",
      "to": "GPIO6",
      "at": [
        247.396,
        153.924
      ]
    },
    {
      "from": "KEY_UP",
      "to": "GPIO7",
      "at": [
        196.596,
        148.844
      ]
    },
    {
      "from": "SD_CD",
      "to": "GPIO10",
      "at": [
        33.782,
        241.808
      ]
    },
    {
      "from": "TFT_RST",
      "to": "GPIO3",
      "at": [
        82.55,
        208.788
      ]
    },
    {
      "from": "TFT_MOSI",
      "to": "GPIO12",
      "at": [
        223.52,
        194.056
      ]
    },
    {
      "from": "TFT_BLK",
      "to": "GPIO39",
      "at": [
        15.24,
        191.008
      ]
    },
    {
      "from": "TFT_CLK",
      "to": "GPIO48",
      "at": [
        82.55,
        203.708
      ]
    },
    {
      "from": "KEY_B",
      "to": "GPIO5",
      "at": [
        127.762,
        166.878
      ]
    },
    {
      "from": "TFT_CS",
      "to": "GPIO14",
      "at": [
        82.55,
        201.168
      ]
    },
    {
      "from": "SD_CD",
      "to": "GPIO10",
      "at": [
        98.044,
        258.572
      ]
    },
    {
      "from": "KEY_A",
      "to": "GPIO15",
      "at": [
        127.762,
        156.718
      ]
    },
    {
      "from": "SD_DATA",
      "to": "GPIO9",
      "at": [
        98.044,
        253.492
      ]
    }
  ],
  "annotated_power_symbols": [
    {
      "reference": "#PWR001",
      "lib_id": "Cadenza-re-easyedapro:Ground-GND",
      "uuid": "02aaa5e3-89af-4ee1-b291-7114d8c22917"
    },
    {
      "reference": "#PWR002",
      "lib_id": "Cadenza-re-easyedapro:Power-VCC",
      "uuid": "03147eaa-20f2-4497-b368-0dbc78e70c81"
    },
    {
      "reference": "#PWR003",
      "lib_id": "Cadenza-re-easyedapro:Power-VCC",
      "uuid": "070556ca-538d-498b-b1a0-f99c38a6e6b9"
    },
    {
      "reference": "#PWR004",
      "lib_id": "Cadenza-re-easyedapro:Ground-GND",
      "uuid": "07186cd4-bd18-4e0d-a5fc-cdae401f3664"
    },
    {
      "reference": "#PWR005",
      "lib_id": "Cadenza-re-easyedapro:Ground-GND",
      "uuid": "0941544b-6d77-4647-a33d-5ba51a09876c"
    },
    {
      "reference": "#PWR006",
      "lib_id": "Cadenza-re-easyedapro:Ground-GND",
      "uuid": "0d7bd9ce-75e3-433f-9364-e53fcdfc3cc5"
    },
    {
      "reference": "#PWR007",
      "lib_id": "Cadenza-re-easyedapro:Ground-GND",
      "uuid": "0f73fd99-d786-4290-8cd1-e6b4764d1dda"
    },
    {
      "reference": "#PWR008",
      "lib_id": "Cadenza-re-easyedapro:Ground-GND",
      "uuid": "13557f47-0982-42b9-b953-599e7031b180"
    },
    {
      "reference": "#PWR009",
      "lib_id": "Cadenza-re-easyedapro:Ground-GND",
      "uuid": "1feee81b-1c21-4555-82ca-16f3986a01a4"
    },
    {
      "reference": "#PWR010",
      "lib_id": "Cadenza-re-easyedapro:Ground-GND",
      "uuid": "20e75e87-7329-40e9-9c0d-48576e113f1f"
    },
    {
      "reference": "#PWR011",
      "lib_id": "Cadenza-re-easyedapro:Ground-GND",
      "uuid": "263ff25e-d297-4f3f-87e3-d9df3118c8b1"
    },
    {
      "reference": "#PWR012",
      "lib_id": "Cadenza-re-easyedapro:Ground-GND",
      "uuid": "2dd2a180-b15c-4416-867c-f84ecb105450"
    },
    {
      "reference": "#PWR013",
      "lib_id": "Cadenza-re-easyedapro:Ground-GND",
      "uuid": "2eae8b62-a696-42e1-ace9-92fd95b9891e"
    },
    {
      "reference": "#PWR014",
      "lib_id": "Cadenza-re-easyedapro:Ground-GND",
      "uuid": "2ec1f40c-3927-48f7-937f-15443de23e8d"
    },
    {
      "reference": "#PWR015",
      "lib_id": "Cadenza-re-easyedapro:Ground-GND",
      "uuid": "2ffb01d3-5d21-4deb-8a10-46819cf445d8"
    },
    {
      "reference": "#PWR016",
      "lib_id": "Cadenza-re-easyedapro:Power-VCC",
      "uuid": "38b0957e-1dec-472a-a77e-0351e15e42d7"
    },
    {
      "reference": "#PWR017",
      "lib_id": "Cadenza-re-easyedapro:Ground-GND",
      "uuid": "3cd76ff5-5050-4e4c-88d2-7d949497c312"
    },
    {
      "reference": "#PWR018",
      "lib_id": "Cadenza-re-easyedapro:Ground-GND",
      "uuid": "41007079-e9ff-4093-897f-753f9230c7fd"
    },
    {
      "reference": "#PWR019",
      "lib_id": "Cadenza-re-easyedapro:Ground-GND",
      "uuid": "418ff0fe-1f16-4ae9-8e1c-7ad297eec73a"
    },
    {
      "reference": "#PWR020",
      "lib_id": "Cadenza-re-easyedapro:Ground-GND",
      "uuid": "42426882-726b-4604-8497-d74dfd806c5c"
    },
    {
      "reference": "#PWR021",
      "lib_id": "Cadenza-re-easyedapro:Ground-GND",
      "uuid": "4640da2e-b953-4f7a-b368-dcabcf4d8a42"
    },
    {
      "reference": "#PWR022",
      "lib_id": "Cadenza-re-easyedapro:Ground-GND",
      "uuid": "4a910aee-a0b2-4f9a-9c8b-8f1f918b92b7"
    },
    {
      "reference": "#PWR023",
      "lib_id": "Cadenza-re-easyedapro:Ground-GND",
      "uuid": "50146d70-b83f-42d9-8882-4b51b53df12d"
    },
    {
      "reference": "#PWR024",
      "lib_id": "Cadenza-re-easyedapro:Power-5V",
      "uuid": "50f20543-8b16-4bfb-a9d6-3662bb590191"
    },
    {
      "reference": "#PWR025",
      "lib_id": "Cadenza-re-easyedapro:Ground-GND",
      "uuid": "51ccff71-4376-4689-a50d-27958c0e73c8"
    },
    {
      "reference": "#PWR026",
      "lib_id": "Cadenza-re-easyedapro:Power-VCC",
      "uuid": "524f9055-5f02-4ddb-bdeb-935f87ba3b52"
    },
    {
      "reference": "#PWR027",
      "lib_id": "Cadenza-re-easyedapro:Ground-GND",
      "uuid": "538bb2b4-7b43-41c4-abf3-8cd7699b2add"
    },
    {
      "reference": "#PWR028",
      "lib_id": "Cadenza-re-easyedapro:Ground-GND",
      "uuid": "53f3738a-c53a-4367-9802-da7150d3799d"
    },
    {
      "reference": "#PWR029",
      "lib_id": "Cadenza-re-easyedapro:Ground-GND",
      "uuid": "55c251e4-361f-4cc1-bcc7-cc89fba3db44"
    },
    {
      "reference": "#PWR030",
      "lib_id": "Cadenza-re-easyedapro:Ground-GND",
      "uuid": "6030c86a-38c1-4865-ac3f-92f392ac22ea"
    },
    {
      "reference": "#PWR031",
      "lib_id": "Cadenza-re-easyedapro:Ground-GND",
      "uuid": "64107a9d-9df2-40f2-9c11-94a4286b0108"
    },
    {
      "reference": "#PWR032",
      "lib_id": "Cadenza-re-easyedapro:Ground-GND",
      "uuid": "69e86413-966f-4706-94c3-ad600ff6cc7d"
    },
    {
      "reference": "#PWR033",
      "lib_id": "Cadenza-re-easyedapro:Power-VCC",
      "uuid": "7687f1d0-2d5d-47c2-b55e-4986a4cb917c"
    },
    {
      "reference": "#PWR034",
      "lib_id": "Cadenza-re-easyedapro:Power-VCC",
      "uuid": "813a03cb-c13a-4230-9ae1-dc9f8b99bbc9"
    },
    {
      "reference": "#PWR035",
      "lib_id": "Cadenza-re-easyedapro:Ground-GND",
      "uuid": "863cd2b7-b2cb-4983-9493-62114ca26b06"
    },
    {
      "reference": "#PWR036",
      "lib_id": "Cadenza-re-easyedapro:Power-5V",
      "uuid": "89781196-27a8-4477-bf2b-39f8fde9122b"
    },
    {
      "reference": "#PWR037",
      "lib_id": "Cadenza-re-easyedapro:Ground-GND",
      "uuid": "8e7aae1f-0678-44fc-a55a-226a6d0bec1c"
    },
    {
      "reference": "#PWR038",
      "lib_id": "Cadenza-re-easyedapro:Ground-GND",
      "uuid": "8ebbce5b-cc29-420a-80f8-658e476278fc"
    },
    {
      "reference": "#PWR039",
      "lib_id": "Cadenza-re-easyedapro:Ground-GND",
      "uuid": "91247dd3-670a-41b0-a573-561734f014ec"
    },
    {
      "reference": "#PWR040",
      "lib_id": "Cadenza-re-easyedapro:Ground-GND",
      "uuid": "977b0f1e-dce1-4bb3-9d39-6a37fbd4e708"
    },
    {
      "reference": "#PWR041",
      "lib_id": "Cadenza-re-easyedapro:Ground-GND",
      "uuid": "97bc2f5b-403c-4879-a9d4-01050d08068e"
    },
    {
      "reference": "#PWR042",
      "lib_id": "Cadenza-re-easyedapro:Power-VCC",
      "uuid": "991eab8b-a6d2-4205-8567-a20d1e19d00b"
    },
    {
      "reference": "#PWR043",
      "lib_id": "Cadenza-re-easyedapro:Ground-GND",
      "uuid": "9a292749-b421-4d5c-b16a-42cb9dc0c818"
    },
    {
      "reference": "#PWR044",
      "lib_id": "Cadenza-re-easyedapro:Ground-GND",
      "uuid": "9b27635b-0cc2-4e37-be2a-da25aff1c9b1"
    },
    {
      "reference": "#PWR045",
      "lib_id": "Cadenza-re-easyedapro:Power-VCC",
      "uuid": "9ea2d8ed-e959-4614-b639-faf3b3e4071a"
    },
    {
      "reference": "#PWR046",
      "lib_id": "Cadenza-re-easyedapro:Ground-GND",
      "uuid": "a5dcb84e-d48c-4503-a2bf-36d29b9753c3"
    },
    {
      "reference": "#PWR047",
      "lib_id": "Cadenza-re-easyedapro:Ground-GND",
      "uuid": "a86446aa-3f06-4a51-91f3-3eb44364b1d7"
    },
    {
      "reference": "#PWR048",
      "lib_id": "Cadenza-re-easyedapro:Ground-GND",
      "uuid": "ae6bd9b2-d9ec-40f7-a47a-10f09d03f3e1"
    },
    {
      "reference": "#PWR049",
      "lib_id": "Cadenza-re-easyedapro:Ground-GND",
      "uuid": "af288dda-3ffc-4e52-b07e-cabb2d1fbbf1"
    },
    {
      "reference": "#PWR050",
      "lib_id": "Cadenza-re-easyedapro:Ground-GND",
      "uuid": "b14fe1b9-418a-41af-b9ad-3405db7c3f87"
    },
    {
      "reference": "#PWR051",
      "lib_id": "Cadenza-re-easyedapro:Power-VCC",
      "uuid": "baf273cd-da77-4819-8a28-c0b1f97633a2"
    },
    {
      "reference": "#PWR052",
      "lib_id": "Cadenza-re-easyedapro:Power-5V",
      "uuid": "bbcbaf8c-9966-4d52-845f-609a53609796"
    },
    {
      "reference": "#PWR053",
      "lib_id": "Cadenza-re-easyedapro:Ground-GND",
      "uuid": "bcebe182-1ef3-4f2f-b7bc-688889622a1e"
    },
    {
      "reference": "#PWR054",
      "lib_id": "Cadenza-re-easyedapro:Ground-GND",
      "uuid": "c104ccc1-b66f-46db-b297-41ef0349e4b3"
    },
    {
      "reference": "#PWR055",
      "lib_id": "Cadenza-re-easyedapro:Ground-GND",
      "uuid": "c1545857-dcc6-4bdb-a59b-0cd3756e0751"
    },
    {
      "reference": "#PWR056",
      "lib_id": "Cadenza-re-easyedapro:Ground-GND",
      "uuid": "c2d2b70c-0bb6-41db-9cc8-77552059a9b5"
    },
    {
      "reference": "#PWR057",
      "lib_id": "Cadenza-re-easyedapro:Ground-GND",
      "uuid": "c433592f-1e6a-4128-8e7a-6d75266e9ab2"
    },
    {
      "reference": "#PWR058",
      "lib_id": "Cadenza-re-easyedapro:Ground-GND",
      "uuid": "cfc47503-62c8-4444-a6c9-c992f88cf37c"
    },
    {
      "reference": "#PWR059",
      "lib_id": "Cadenza-re-easyedapro:Ground-GND",
      "uuid": "d2a4171b-2a2a-44ac-bb0a-c60fae20d209"
    },
    {
      "reference": "#PWR060",
      "lib_id": "Cadenza-re-easyedapro:Ground-GND",
      "uuid": "d4e8dac7-dcf7-4ade-b30b-e463a78908c9"
    },
    {
      "reference": "#PWR061",
      "lib_id": "Cadenza-re-easyedapro:Ground-GND",
      "uuid": "d6d397eb-284f-458f-9032-6716d109fb04"
    },
    {
      "reference": "#PWR062",
      "lib_id": "Cadenza-re-easyedapro:Power-VCC",
      "uuid": "ecbe63f0-40d4-4942-8a34-7878fc4d5320"
    },
    {
      "reference": "#PWR063",
      "lib_id": "Cadenza-re-easyedapro:Power-VCC",
      "uuid": "ef3683ab-2bf9-4950-bfb2-1bf0610810d4"
    },
    {
      "reference": "#PWR064",
      "lib_id": "Cadenza-re-easyedapro:Power-VCC",
      "uuid": "f115a7ad-1825-4481-ac43-9119bd3d1202"
    },
    {
      "reference": "#PWR065",
      "lib_id": "Cadenza-re-easyedapro:Ground-GND",
      "uuid": "f6fc41b4-a734-4e2b-b0c8-ebe2a4cfc605"
    },
    {
      "reference": "#PWR066",
      "lib_id": "Cadenza-re-easyedapro:Ground-GND",
      "uuid": "fb7e9017-e1f6-4ac9-a033-6080f519b068"
    },
    {
      "reference": "#PWR067",
      "lib_id": "Cadenza-re-easyedapro:Ground-GND",
      "uuid": "fcd0d0b6-b2f4-4b20-9d55-01bdb825d5bd"
    },
    {
      "reference": "#PWR068",
      "lib_id": "Cadenza-re-easyedapro:Ground-GND",
      "uuid": "fd9997bb-207d-4b2b-a737-c4242fd7813b"
    },
    {
      "reference": "#PWR069",
      "lib_id": "Cadenza-re-easyedapro:Ground-GND",
      "uuid": "fe7e6d86-740d-46ce-ab3b-018f78c8c969"
    }
  ]
}
